cacheia_decorators/__init__.py
cacheia_decorators/local.py
cacheia_decorators/remote.py
cacheia_decorators-1.0.0.post3.dist-info/METADATA
cacheia_decorators-1.0.0.post3.dist-info/WHEEL
cacheia_decorators-1.0.0.post3.dist-info/top_level.txt
cacheia_decorators-1.0.0.post3.dist-info/RECORD
