Metadata-Version: 2.1
Name: cacheia_decorators
Version: 1.0.0.post3
Summary: Decorates for Cacheia library that allows invalidation and other shenanigans
Author-email: TeiaLabs <contato@teialabs.com>
Keywords: cache,decorator,method
Requires-Python: >=3.12
Provides-Extra: dev
Requires-Dist: black <25,>=24 ; extra == 'dev'
Requires-Dist: isort <6,>=5 ; extra == 'dev'
Requires-Dist: pytest <9,>=8 ; extra == 'dev'
Provides-Extra: local
Requires-Dist: cacheia ==1.0.0 ; extra == 'local'
Provides-Extra: remote
Requires-Dist: cacheia-client ==1.0.0 ; extra == 'remote'
Provides-Extra: schemas
Requires-Dist: cacheia-schemas ==1.0.0 ; extra == 'schemas'
